diploSHIC-1.0.7.data/scripts/diploSHIC
diploSHIC-1.0.7.data/scripts/makeFeatureVecsForChrArmFromVcfDiploid.py
diploSHIC-1.0.7.data/scripts/makeFeatureVecsForChrArmFromVcf_ogSHIC.py
diploSHIC-1.0.7.data/scripts/makeFeatureVecsForSingleMsDiploid.py
diploSHIC-1.0.7.data/scripts/makeFeatureVecsForSingleMs_ogSHIC.py
diploSHIC-1.0.7.data/scripts/makeTrainingSets.py
diploSHIC.libs/libgfortran-040039e1.so.5.0.0
diploSHIC.libs/libquadmath-96973f99.so.0.0.0
diploshic/__init__.py
diploshic/fvTools.py
diploshic/generateSimLaunchScript.py
diploshic/makeFeatureVecsForChrArmFromVcfDiploid.py
diploshic/makeFeatureVecsForChrArmFromVcf_ogSHIC.py
diploshic/makeFeatureVecsForSingleMsDiploid.py
diploshic/makeFeatureVecsForSingleMs_ogSHIC.py
diploshic/makeTrainingSets.py
diploshic/misc.py
diploshic/msTools.py
diploshic/setup.py
diploshic/shicstats.cpython-38-x86_64-linux-gnu.so
diploSHIC-1.0.7.dist-info/LICENSE
diploSHIC-1.0.7.dist-info/METADATA
diploSHIC-1.0.7.dist-info/WHEEL
diploSHIC-1.0.7.dist-info/top_level.txt
diploSHIC-1.0.7.dist-info/RECORD
