Metadata-Version: 2.1
Name: diploSHIC
Version: 1.0.7
Summary: diploSHIC
Home-page: https://github.com/kr-colab/diploSHIC
Author: Andrew Kern
Author-email: adkern@uoregon.edu
License: MIT
Platform: UNKNOWN
Requires-Python: <3.12,>=3.10
License-File: LICENSE
Requires-Dist: numpy
Requires-Dist: scipy
Requires-Dist: matplotlib
Requires-Dist: pandas
Requires-Dist: scikit-allel
Requires-Dist: scikit-learn
Requires-Dist: tensorflow==2.15.0
Requires-Dist: keras
Provides-Extra: dev
